karrio/mappers/allied_express/__init__.py
karrio/mappers/allied_express/mapper.py
karrio/mappers/allied_express/proxy.py
karrio/mappers/allied_express/settings.py
karrio/plugins/allied_express/__init__.py
karrio/providers/allied_express/__init__.py
karrio/providers/allied_express/error.py
karrio/providers/allied_express/rate.py
karrio/providers/allied_express/tracking.py
karrio/providers/allied_express/units.py
karrio/providers/allied_express/utils.py
karrio/providers/allied_express/shipment/__init__.py
karrio/providers/allied_express/shipment/cancel.py
karrio/providers/allied_express/shipment/create.py
karrio/schemas/allied_express/__init__.py
karrio/schemas/allied_express/label_request.py
karrio/schemas/allied_express/label_response.py
karrio/schemas/allied_express/rate_request.py
karrio/schemas/allied_express/rate_response.py
karrio/schemas/allied_express/tracking_request.py
karrio/schemas/allied_express/tracking_response.py
karrio/schemas/allied_express/void_request.py
karrio/schemas/allied_express/void_response.py
karrio_allied_express-2026.1.4.dist-info/METADATA
karrio_allied_express-2026.1.4.dist-info/WHEEL
karrio_allied_express-2026.1.4.dist-info/entry_points.txt
karrio_allied_express-2026.1.4.dist-info/top_level.txt
karrio_allied_express-2026.1.4.dist-info/RECORD
